mathfancy/__init__.py
mathfancy-0.1.0.dist-info/METADATA
mathfancy-0.1.0.dist-info/WHEEL
mathfancy-0.1.0.dist-info/top_level.txt
mathfancy-0.1.0.dist-info/RECORD
