Metadata-Version: 2.4
Name: mathfancy
Version: 0.1.0
Summary: Convert plain text to fancy Unicode math styles
Author-email: liujunyi <liujunyi0702@petalmail.com>
License: MIT
Keywords: unicode,fonts,math,style
Classifier: Programming Language :: Python :: 3
Classifier: License :: OSI Approved :: MIT License
Classifier: Operating System :: OS Independent
Requires-Python: >=3.0
